pysolnp.cpython-38-x86_64-linux-gnu.so
pysolnp-2025.10.17.data/data/requirements-dev.txt
pysolnp.libs/libgcc_s-0cd532bd.so.1
pysolnp.libs/libstdc++-5d72f927.so.6.0.33
python_solnp/README.md
python_solnp/__init__.py
python_solnp/pysolver.cpp
python_solnp/pysolver.hpp
python_solnp/examples/__init__.py
python_solnp/examples/example_alkyla.py
python_solnp/examples/example_box.py
python_solnp/examples/example_powell.py
python_solnp/examples/example_rosen_suzuki.py
python_solnp/examples/example_simple_quadratic.py
python_solnp/examples/example_wright_four.py
python_solnp/test/__init__.py
python_solnp/test/test.py
pysolnp-2025.10.17.dist-info/LICENSE.md
pysolnp-2025.10.17.dist-info/METADATA
pysolnp-2025.10.17.dist-info/WHEEL
pysolnp-2025.10.17.dist-info/top_level.txt
pysolnp-2025.10.17.dist-info/RECORD
