Metadata-Version: 2.1
Name: pysolnp
Version: 2025.10.17
Summary: This provides the SOLNP optimization Algorithm.
Home-page: https://github.com/KristerSJakobsson/solnp
Author: Krister Sune Jakobsson
Author-email: krister.s.jakobsson@gmail.com
License: Boost Software License
Classifier: Programming Language :: Python :: 3
Classifier: Programming Language :: Python :: 3.8
Classifier: Programming Language :: Python :: 3.9
Classifier: Programming Language :: Python :: 3.10
Classifier: Programming Language :: Python :: 3.11
Classifier: Programming Language :: Python :: 3.12
Classifier: Programming Language :: Python :: 3.13
Classifier: Programming Language :: Python :: 3.14
Classifier: Programming Language :: C++
Classifier: Operating System :: MacOS :: MacOS X
Classifier: Operating System :: Microsoft :: Windows
Classifier: Operating System :: POSIX :: Linux
Classifier: Development Status :: 6 - Mature
Requires-Python: >=3.8
License-File: LICENSE.md
Provides-Extra: dev
Requires-Dist: autopep8>=1.6.0; extra == "dev"
Requires-Dist: pytest>=7.0.1; extra == "dev"
